Workbook

Sheet Assumptions
A1: 3-Year Revenue & Gross Profit Template (Fill in Yellow Cells)
A3: Category | B3: Metric | C3: Unit | D3: Year 1 | E3: Year 2 | F3: Year 3 | G3: Notes | H3: Source / Evidence ID
A4: Theme Camp | B4: Paid participants (unique) | C4: people | G4: Participants who paid for 7/14-day camps | H4: E-
A5: Theme Camp | B5: Avg camp price (blended) | C5: CNY/person | G5: Weighted avg across 7-day & 14-day products | H5: E-
A6: Theme Camp | B6: Cost per participant (variable) | C6: CNY/person | G6: Delivery costs: TA/ops, materials, tools | H6: E-
A7: Membership | B7: Active members (avg monthly) | C7: people | G7: Average number of paying members per month | H7: E-
A8: Membership | B8: Avg membership price (blended) | C8: CNY/member/month | G8: Blended monthly revenue per active member | H8: E-
A9: Membership | B9: Cost per active member (variable) | C9: CNY/member/month | G9: Support, tools, content updates, ops | H9: E-
A10: Goods | B10: Purchasing users (unique) | C10: people | G10: Users who placed ≥1 order in the year | H10: E-
A11: Goods | B11: Orders per purchasing user | C11: orders/user/year | G11: Average annual purchase frequency | H11: E-
A12: Goods | B12: Average order value (AOV) | C12: CNY/order | G12: Revenue per order (incl. bundles) | H12: E-
A13: Goods | B13: Gross margin rate | C13: % | G13: Gross margin on goods revenue (after COGS & variable fulfillment) | H13: E-
A16: Quick Checks
A17: • If you sell both 7-day & 14-day camps, set blended price accordingly.
A18: • Gross margin rate is for goods only; camp & membership use variable costs above.
A19: • Use your MVP evidence IDs (E-xx) in Source / Evidence ID column.

Sheet Revenue_Breakdown
A1: Three-Year Revenue Breakdown (Revenue & Gross Profit)
A4: Line Item | B4: Year 1 | C4: Year 2 | D4: Year 3 | E4: Formula / Driver | F4: Unit | G4: Input Source (Assumptions) | H4: Notes
A5: Theme Camp Revenue | B5: =Assumptions!D4*Assumptions!D5 | C5: =Assumptions!E4*Assumptions!E5 | D5: =Assumptions!F4*Assumptions!F5 | E5: Participants × Avg price | F5: CNY | G5: Assumptions (Theme Camp) | H5: Content paid products (7/14-day)
A6: Theme Camp Variable Cost | B6: =Assumptions!D4*Assumptions!D6 | C6: =Assumptions!E4*Assumptions!E6 | D6: =Assumptions!F4*Assumptions!F6 | E6: Participants × Cost/participant | F6: CNY | G6: Assumptions (Theme Camp) | H6: Ops/TA/tools per participant
A7: Theme Camp Gross Profit | B7: =B6-B7 | C7: =C6-C7 | D7: =D6-D7 | E7: Revenue − Variable cost | F7: CNY | G7: Calculated | H7: Gross profit for camps
A9: Membership Revenue | B9: =Assumptions!D7*Assumptions!D8*12 | C9: =Assumptions!E7*Assumptions!E8*12 | D9: =Assumptions!F7*Assumptions!F8*12 | E9: Avg monthly members × Price/month × 12 | F9: CNY | G9: Assumptions (Membership) | H9: Blended membership revenue
A10: Membership Variable Cost | B10: =Assumptions!D7*Assumptions!D9*12 | C10: =Assumptions!E7*Assumptions!E9*12 | D10: =Assumptions!F7*Assumptions!F9*12 | E10: Avg monthly members × Cost/member/month × 12 | F10: CNY | G10: Assumptions (Membership) | H10: Support & tools per member
A11: Membership Gross Profit | B11: =B10-B11 | C11: =C10-C11 | D11: =D10-D11 | E11: Revenue − Variable cost | F11: CNY | G11: Calculated | H11: Gross profit for membership
A13: Goods Revenue | B13: =Assumptions!D10*Assumptions!D11*Assumptions!D12 | C13: =Assumptions!E10*Assumptions!E11*Assumptions!E12 | D13: =Assumptions!F10*Assumptions!F11*Assumptions!F12 | E13: Purchasing users × Orders/user × AOV | F13: CNY | G13: Assumptions (Goods) | H13: Total goods GMV / revenue
A14: Goods Gross Profit | B14: =B14*Assumptions!D13 | C14: =C14*Assumptions!E13 | D14: =D14*Assumptions!F13 | E14: Goods Revenue × Gross margin rate | F14: CNY | G14: Assumptions (Goods) | H14: Gross profit after COGS & variable fulfillment
A16: Total Revenue (Camps + Membership + Goods) | B16: =B6+B10+B14 | C16: =C6+C10+C14 | D16: =D6+D10+D14 | E16: Sum of revenue lines | F16: CNY | G16: Calculated | H16: Top-line revenue
A17: Total Gross Profit | B17: =B8+B12+B15 | C17: =C8+C12+C15 | D17: =D8+D12+D15 | E17: Sum of gross profit lines | F17: CNY | G17: Calculated | H17: Total gross profit

Sheet Notes
A1: How to Use
A3: 1) Fill all yellow cells in the Assumptions sheet for Year 1–Year 3.
A4: 2) Revenue_Breakdown will calculate revenue and gross profit automatically (green cells).
A5: 3) Use consistent units (CNY) and keep assumptions conservative for competition judging.
A6: 4) Put your evidence IDs (E-xx) in Assumptions column H to prove assumptions.
A8: Tips for Conservative Assumptions
A9: • Start with low conversion rates and modest AOV; focus on improving retention and repeat purchases.
A10: • Keep goods gross margin modest if using distribution/affiliate models.
A11: • Track variable costs carefully; service-heavy models can leak margin if support scales poorly.
